.gitignore
LICENSE
Makefile
README.md
build.sh
setup.cfg
setup.py
upload.sh
.circleci/config.yml
pandoc_pandocker_filters/AAFigure.py
pandoc_pandocker_filters/BitField.py
pandoc_pandocker_filters/ListingTable.py
pandoc_pandocker_filters/RotateImage.py
pandoc_pandocker_filters/__init__.py
pandoc_pandocker_filters/aafigure_inline.py
pandoc_pandocker_filters/bitfield_inline.py
pandoc_pandocker_filters/filter.py
pandoc_pandocker_filters/listingtable_inline.py
pandoc_pandocker_filters/pantable_inline.py
pandoc_pandocker_filters/rotateimage_inline.py
pandoc_pandocker_filters/rotatesvg.py
pandoc_pandocker_filters/wavedrom_inline.py
pandoc_pandocker_filters.egg-info/PKG-INFO
pandoc_pandocker_filters.egg-info/SOURCES.txt
pandoc_pandocker_filters.egg-info/dependency_links.txt
pandoc_pandocker_filters.egg-info/entry_points.txt
pandoc_pandocker_filters.egg-info/requires.txt
pandoc_pandocker_filters.egg-info/top_level.txt
tests/.gitignore
tests/Makefile
tests/data/aafigure.txt
tests/data/items.csv
tests/data/table.csv
tests/data/bitfields/bit.json
tests/data/bitfields/bit.yaml
tests/data/waves/anotherwave.yaml
tests/data/waves/commandSandP_wo.yaml
tests/data/waves/commandSandP_wo_bus.yaml
tests/data/waves/commandSandP_wo_ret.yaml
tests/data/waves/wave.yaml
tests/markdown/TITLE.md
tests/markdown/config.yaml