Metadata-Version: 1.2
Name: pandoc-pandocker-filters
Version: 0.1
Summary: Yet another set of pandoc filters
Home-page: https://github.com/K4zuki/pandocker-filters
Author: k4zuki
Author-email: k.yamamoto.08136891@gmail.com
License: MIT
Keywords: pandoc,markdown
Platform: UNKNOWN
Classifier: Development Status :: 4 - Beta
Classifier: Programming Language :: Python :: 3.5
Classifier: Programming Language :: Python :: 3.6
Requires-Python: >=3.5,!=3.0.*,!=3.1.*,!=3.2.*
